LICENSE
MANIFEST.in
README.md
VERSION
setup.py
riemann_fping/__init__.py
riemann_fping/fping.py
riemann_fping/riemann_fping.py
riemann_fping/transport.py
riemann_fping.egg-info/PKG-INFO
riemann_fping.egg-info/SOURCES.txt
riemann_fping.egg-info/dependency_links.txt
riemann_fping.egg-info/entry_points.txt
riemann_fping.egg-info/requires.txt
riemann_fping.egg-info/top_level.txt
riemann_fping/tests/__init__.py
riemann_fping/tests/test_fping.py