Metadata-Version: 1.1
Name: riemann-fping
Version: 0.1.dev2
Summary: Ping data collector for RIEMANN
Home-page: https://github.com/node13h/riemann-fping
Author: Sergej Alikov
Author-email: sergej.alikov@gmail.com
License: GPL-3.0
Keywords: riemann ping fping
Platform: UNKNOWN
Classifier: Development Status :: 3 - Alpha
Classifier: Intended Audience :: Telecommunications Industry
Classifier: License :: OSI Approved :: GNU General Public License v3 or later (GPLv3+)
Classifier: Programming Language :: Python :: 3
